EagleEyev3/__init__.py
EagleEyev3/_version.py
EagleEyev3/camera.py
EagleEyev3/device.py
EagleEyev3/eagleeyev3.py
eagleeyev3-0.0.25.dist-info/LICENSE
eagleeyev3-0.0.25.dist-info/WHEEL
eagleeyev3-0.0.25.dist-info/METADATA
eagleeyev3-0.0.25.dist-info/RECORD
