Metadata-Version: 2.1
Name: EagleEyev3
Version: 0.0.25
Summary: Python client for Eagle Eye Networks APIv3 
Author-email: mcotton <mcotton@mcottondesign.com>
Classifier: License :: OSI Approved :: MIT License
Project-URL: Home, https://mcotton.space
Project-URL: Source, https://git.mcotton.space/mcotton/EagleEyev3
